footprint_facility/__init__.py
footprint_facility/_version.py
footprint_facility/footprint_facility.py
footprint_facility/footprint_statistcs.py
footprint_facility/tests/__init__.py
footprint_facility/tests/test_footprint_facility.py
footprint_facility/tests/test_footprint_statistics.py
footprint_facility/tests/test_utilities.py
footprint_facility-1.11.dist-info/licenses/LICENCE.txt
footprint_facility-1.11.dist-info/METADATA
footprint_facility-1.11.dist-info/WHEEL
footprint_facility-1.11.dist-info/entry_points.txt
footprint_facility-1.11.dist-info/top_level.txt
footprint_facility-1.11.dist-info/RECORD
