Metadata-Version: 2.4
Name: footprint_facility
Version: 1.11
Summary: Footprint Facility Library
Author: GAEL Systems
Author-email: dev@gael.fr
License: Apache-2.0
Classifier: Programming Language :: Python :: 3.8
Classifier: Environment :: Plugins
Classifier: License :: OSI Approved :: Apache Software License
Classifier: Operating System :: OS Independent
Requires-Python: >=3.8
License-File: LICENCE.txt
Requires-Dist: pyproj~=3.6.1
Requires-Dist: numpy~=1.26.4
Requires-Dist: shapely~=2.0.3
Requires-Dist: geojson~=3.1.0
Requires-Dist: matplotlib~=3.10.0
Requires-Dist: folium~=0.19.4
Requires-Dist: mapclassify~=2.8.1
Requires-Dist: geopandas~=1.0.1
Dynamic: license-file
